{
  "id": "0x33c460400bee3d1333daf2c4f2201e0b819330f2",
  "timestamp": 1713548981000,
  "author": {
    "username": "ryanthompson",
    "displayname": "Ryan",
    "fid": 340870,
    "avatar": "https://i.imgur.com/Cv8B5uD.jpg",
    "description": "Artist and Book Publisher\nwww.objkt.com/@ryanthompson\nwww.ryanthompson.name"
  },
  "text": "Nancy Burson, a pioneer of synthetic photography, developed a system to fuse multiple images in to a new composite. One of her early explorations in the late 70's was the \"aged\" transformation, taking a photo of a person and predicting what they would look like later in life. Reminiscent of GANs but 35+ years before.",
  "images": [
    "https://imagedelivery.net/BXluQx4ige9GuW0Ia56BHw/87efa5c9-3014-4efc-7f71-ea2424f60c00/original",
    "https://imagedelivery.net/BXluQx4ige9GuW0Ia56BHw/b8594213-43b6-46ec-96f6-4ea0f6652700/original"
  ]
}