{
  "id": "0x4ce3162d36b34e88a16275308b3c2bc0980f17f2",
  "timestamp": 1715108067000,
  "author": {
    "username": "duaneking",
    "displayname": "kingd.eth",
    "fid": 3189,
    "avatar": "https://i.imgur.com/n5BLfWV.gif",
    "description": "ᴄᴜʀɪᴏsɪᴛʏ ▁▂▃▄▅▆▇ 100%\nɴᴏᴡ ᴘʟᴀʏɪɴɢ ──────⚪──\n ⇄   ◃◃   ⅠⅠ   ▹▹   ↻\nduaneking.twitter"
  },
  "text": "Communicology, Vilém Flusser, 1978\n\nFlusser’s observations on media theory and the massive transitions in the way we communicate alongside concepts of the technical image and technical imagination shed wisdom and light on contemporary media.",
  "images": [
    "https://imagedelivery.net/BXluQx4ige9GuW0Ia56BHw/2d6af5cd-f485-4a2f-f092-60d435d6f800/original"
  ]
}