{
  "id": "0x5c4b83e3eb35614bfefe3e3efaf43e1d8a4ff876",
  "timestamp": 1713114323000,
  "author": {
    "username": "v3ga",
    "displayname": "Julien Gachadoat",
    "fid": 252572,
    "avatar": "https://i.imgur.com/qbAHP5q.jpg",
    "description": "Generative artist based in Bordeaux (FR)"
  },
  "text": "New Grammar of Ornament • Thomas Weil • Lars Müller Publishers • 2021\n\n\"The author compares current ornamental objects with the results of archaeological research on ornamental artifacts and concludes that there is an anthropological constant\"",
  "images": [
    "https://imagedelivery.net/BXluQx4ige9GuW0Ia56BHw/0fc2e684-eca1-45df-cec0-32874ef3d800/original",
    "https://imagedelivery.net/BXluQx4ige9GuW0Ia56BHw/f6f3c4b0-a336-42e8-b18d-60af8027e600/original"
  ]
}