{
  "id": "0x6bc399ec28450578025ae7d0ac1eb3016c10d1af",
  "timestamp": 1723525946000,
  "author": {
    "username": "paul-prudence",
    "displayname": "Paul Prudence",
    "fid": 307224,
    "avatar": "https://i.imgur.com/1wOpavr.jpg",
    "description": "Artist & Writer /the-library ✷ /geoblocks ✷ https://linktr.ee/paulprudence ✷ https://twitter.com/MrPrudence\n\n"
  },
  "text": "Waves – The Art of the Electromagnetic Society (Exhibition Catalogue, Hartware MedienKunstVerein, 2008)\n\nThe book presents artworks that regard electromagnetic waves not only as carriers of information but also as artistic materials and mediums connecting people, nature, and technology\n\n↓↓↓ For more impressions.",
  "images": [
    "https://imagedelivery.net/BXluQx4ige9GuW0Ia56BHw/e0250f92-f22e-4313-dea3-3b4bde818000/original"
  ]
}