{
  "id": "0x8e942d6ad1c3da65e2df8583590ab8b4cab424a0",
  "timestamp": 1728938992000,
  "author": {
    "username": "vortac",
    "displayname": "tim/vortac",
    "fid": 209586,
    "avatar": "https://i.imgur.com/TKcfxSt.png",
    "description": "Hosting /the-library /deca /newmasters\n— Graphic designer / Creative technologist / solving problems with design and code / Generative Art and Design / Web3"
  },
  "text": "Ed Templeton \"The Cemetery of Reason\", S.M.A.K. 2010\n\nThe book was published on the occasion of the s/t exhibition by Ed Templeton, presented at the Stedelijk Museum voor Actuele Kunst, Ghent, April 3, 2010 to June, 13 2010\n\nSigned copy by the artist\n\nA🧵 – 1/4",
  "images": [
    "https://imagedelivery.net/BXluQx4ige9GuW0Ia56BHw/0920e8bb-c64c-4d72-48d7-961968d67600/original",
    "https://imagedelivery.net/BXluQx4ige9GuW0Ia56BHw/ccabc300-9fed-461e-5119-6a82b47c5500/original"
  ]
}