{
  "id": "0x92cc758de0bda74f08165921e8ffe7d5bc102c4e",
  "timestamp": 1715734489000,
  "author": {
    "username": "duaneking",
    "displayname": "kingd.eth",
    "fid": 3189,
    "avatar": "https://i.imgur.com/n5BLfWV.gif",
    "description": "ᴄᴜʀɪᴏsɪᴛʏ ▁▂▃▄▅▆▇ 100%\nɴᴏᴡ ᴘʟᴀʏɪɴɢ ──────⚪──\n ⇄   ◃◃   ⅠⅠ   ▹▹   ↻\nduaneking.twitter"
  },
  "text": "Seeing <—> Making | Room for Thought, Susan Buck-Morss, Kevin McCaughey, Adam Michaels, 2024\n\nA visual exploration of ideas that brings Kevin’s Boot Boys Biz aesthetic to print. Paired with essays by theorist Susan Buck-Morss, the book delivers heavy inspiration.",
  "images": [
    "https://imagedelivery.net/BXluQx4ige9GuW0Ia56BHw/1d1ba0a0-8ea1-4deb-83a0-60c3242f8300/original"
  ]
}