{
  "id": "0x9321f29cfd876aa27ef8369410e42dca01791bcc",
  "timestamp": 1713311318000,
  "author": {
    "username": "pixelsymphony",
    "displayname": "Pixel Symphony ",
    "fid": 232704
  },
  "text": "Four color plates from Wilhelm Ostwald’s ‘Theory of Colour’. 1930.\n\nOstwald explained his theory of color in a series of lectures at the Bauhaus Dessau in 1926 & 1927 and spoke at the World Congress of Advertising in Berlin in 1929. \n\nThe color plates are from the book he wrote two years before his death.",
  "images": [
    "https://imagedelivery.net/BXluQx4ige9GuW0Ia56BHw/914638cc-2c5d-4bbb-262a-7b74f1995600/original"
  ]
}