{
  "id": "0xadf4c892a05870b15bc9cb1733fca01a77b0844c",
  "timestamp": 1721398237000,
  "author": {
    "username": "tocame",
    "displayname": "TOCA ME",
    "fid": 412564,
    "avatar": "https://i.imgur.com/y8vYOsa.jpg",
    "description": "Artworks: https://toca-me.com/artworks.html ~ Events and Info: http://wonderl.ink/@tocame"
  },
  "text": "We Feel Fine: An Almanac of Human Emotion - by Jonathan Harris and Sep Kamvar, Scribner 2009\n\n⬇️ more in comments",
  "images": [
    "https://imagedelivery.net/BXluQx4ige9GuW0Ia56BHw/d33ae329-6a1a-46b4-0ef9-a1210a20fa00/original",
    "https://imagedelivery.net/BXluQx4ige9GuW0Ia56BHw/e9fe9464-d68a-43b1-d7d0-0ec6dc3ab700/original"
  ]
}