{
  "id": "0xb67f328a51e6f0b957089d22077a971e8252355a",
  "timestamp": 1715277608000,
  "author": {
    "username": "paul-prudence",
    "displayname": "Paul Prudence",
    "fid": 307224,
    "avatar": "https://i.imgur.com/1wOpavr.jpg",
    "description": "Artist & Writer /the-library ✷ /geoblocks ✷ https://linktr.ee/paulprudence ✷ https://twitter.com/MrPrudence\n\n"
  },
  "text": "☆ Library Give-Away ☆\n\nWe gained a lot momentum in recent months. Thanks to everyone for making the-library such an invaluable space.\n\nRaffling 1 ed. of Writing New Codes, 3 Pioneers of Computer Art\n\nTo Enter: \n→ Follow /the-library \n→ Leave a comment \n→ Tip any amount of $DEGEN above 50\n\nEnds: 12 May, 18 UTC",
  "images": [
    "https://imagedelivery.net/BXluQx4ige9GuW0Ia56BHw/194b2c1c-ae63-4deb-40a8-4f98cb154500/original"
  ],
  "recast_by": {
    "username": "vortac",
    "displayname": "tim/vortac",
    "fid": 209586,
    "avatar": "https://i.imgur.com/TKcfxSt.png",
    "description": "Hosting /the-library /deca /newmasters\n— Graphic designer / Creative technologist / solving problems with design and code / Generative Art and Design / Web3"
  },
  "recast_hash": "0x33135f7eff72ee137ed91035436cd8607d28cad1"
}