{
  "id": "0xc8ee0bb545df54611c2f2f98e29097efada595f8",
  "timestamp": 1717004585000,
  "author": {
    "username": "danielpearson",
    "displayname": "Daniel Pearson",
    "fid": 369716,
    "avatar": "https://i.imgur.com/Q4UOFcS.gif",
    "description": "Generative art collector and appreciator. \n\nhttps://www.fxhash.xyz/u/dan_pea14\n\nhttps://verse.works/@dan_pea14"
  },
  "text": "Some of @wblut’s Isoverse works as seen in “Tracing the Line: The Art of Drawing Machines and Pen Plotters” @vetro. (Book is pinned in this channel)",
  "images": [
    "https://imagedelivery.net/BXluQx4ige9GuW0Ia56BHw/b5aecbfc-c1f2-4db2-b685-e52946c94700/original"
  ]
}